README.rst
setup.py
gitmit/__init__.py
gitmit/cache.py
gitmit/executor.py
gitmit/mit.py
gitmit/prefix_tree.py
gitmit/repo.py
gitmit.egg-info/PKG-INFO
gitmit.egg-info/SOURCES.txt
gitmit.egg-info/dependency_links.txt
gitmit.egg-info/entry_points.txt
gitmit.egg-info/requires.txt
gitmit.egg-info/top_level.txt