Metadata-Version: 1.0
Name: gitmit
Version: 0.4.1
Summary: Python library to discover commit times of all files under a git repository
Home-page: https://github.com/delfick/gitmit
Author: Stephen Moore
Author-email: delfick755@gmail.com
License: UNKNOWN
Keywords: git,commit,mtime
Platform: UNKNOWN
